<skits>
	<skit>
		<info>LySs</info>
		<info>Ouran High School Host Club</info>
		<info>Soulja Boy Tell 'Em - Super Soak</info>
	</skit>
	<skit>
		<info>Giliage</info>
		<info>Nyan Koi!</info>
		<info>South Park sound clip</info>
	</skit>
	<skit>
		<info>Synbad2</info>
		<info>Gurren Lagann</info>
		<info>Falcon Punch sound clip</info>
	</skit>
	<skit>
		<info>Prophet of Doom</info>
		<info>Hare+Guu</info>
		<info>Doogal sound clip</info>
	</skit>
	<skit>
		<info>Calvin3</info>
		<info>Super Smash Bros. Brawl</info>
		<info>Homestar Runner - Trogdor (Metal Version)</info>
	</skit>
	<skit>
		<info>Tazuto</info>
		<info>MAR</info>
		<info>Family Guy sound clip</info>
	</skit>
	<skit>
		<info>Threvlin</info>
		<info>Claymore</info>
		<info>The Black Mages - Maybe I'm A Lion</info>
	</skit>
	<skit>
		<info>Humnut</info>
		<info>School Days</info>
		<info>Robot Chicken sound clip</info>
	</skit>
	<skit>
		<info>Synbad2</info>
		<info>Naruto</info>
		<info>Baha Men - Who Let the Dogs Out</info>
	</skit>
	<skit>
		<info>DXM</info>
		<info>Hellsing: Order</info>
		<info>The Fifth Element sound clip</info>
	</skit>
	<skit>
		<info>Shirker</info>
		<info>Princess Tutu</info>
		<info>Left 4 Dead 2 sound clip</info>
	</skit>
	<skit>
		<info>Tazuto</info>
		<info>Excel Saga</info>
		<info>Katy Perry - Hot n Cold</info>
	</skit>
	<skit>
		<info>Sherby</info>
		<info>The Melancholy of Haruhi Suzumiya</info>
		<info>Austin Powers in Goldmember sound clip</info>
	</skit>
	<skit>
		<info>Zabkar</info>
		<info>One Piece</info>
		<info>Michael Jackson - Smooth Criminal</info>
	</skit>
	<skit>
		<info>Rspectcopyrightmyass</info>
		<info>Slayers Next</info>
		<info>The Lion King sound clip</info>
	</skit>
	<skit>
		<info>Rspectcopyrightmyass</info>
		<info>Zero no Tsukaima</info>
		<info>Macross Frontier sound clip</info>
	</skit>
	<skit>
		<info>Synbad2</info>
		<info>Gurren Lagann</info>
		<info>Weird Al Yankovic - Eat It</info>
	</skit>
	<skit>
		<info>Darkzi</info>
		<info>Tower of Druaga - Sword of Uruk</info>
		<info>The Tick sound clip</info>
	</skit>
	<skit>
		<info>MAS8705</info>
		<info>Kenichi: The Mightiest Disciple</info>
		<info>Street Fighter 4 &amp; DBZ sound clips </info>
	</skit>
	<skit>
		<info>Shirker</info>
		<info>Death Note</info>
		<info>Eminem - Medicine Ball </info>
	</skit>
</skits>