<skits>
	<skit>
		<info>SSGWNBTD</info>
		<info>Evangelion 2.22</info>
		<info>Ludo</info>
		<info>Anything for You</info>
	</skit>
	<skit>
		<info>SSGWNBTD</info>
		<info>Nichijou</info>
		<info>Rammstein</info>
		<info>B********</info>
	</skit>
	<skit>
		<info>SSGWNBTD</info>
		<info>Redline</info>
		<info>Cake</info>
		<info>The Distance</info>
	</skit>
	<skit>
		<info>SSGWNBTD</info>
		<info>AMV Hell 3</info>
		<info>Dethklok</info>
		<info>Dethharmonic</info>
	</skit>
	<skit>
		<info>SSGWNBTD</info>
		<info>Evangelion 2.22</info>
		<info>Neon Trees</info>
		<info>Animal</info>
	</skit>
	<skit>
		<info>SSGWNBTD</info>
		<info>Azumanga Daioh</info>
		<info>Ke$ha</info>
		<info>Dinosaur</info>
	</skit>
	<skit>
		<info>SSGWNBTD</info>
		<info>AMV Hell 3</info>
		<info>Paul Stanley</info>
		<info>Live to Win</info>
	</skit>
	<skit>
		<info>SSGWNBTD</info>
		<info>Puni Puni Poemy</info>
		<info>Avril Lavigne</info>
		<info>What the Hell</info>
	</skit>
	<skit>
		<info>SSGWNBTD</info>
		<info>Berserk</info>
		<info>Betzefer</info>
		<info>Doomsday</info>
	</skit>
	<skit>
		<info>SSGWNBTD</info>
		<info>Redline</info>
		<info>Dethklok</info>
		<info>Dethharmonic</info>
	</skit>
	<skit>
		<info>SSGWNBTD</info>
		<info>AMV Hell 3</info>
		<info>Trent Reznor and Atticus Ross</info>
		<info>In the Hall of the Mountain King</info>
	</skit>
	<skit>
		<info>SSGWNBTD</info>
		<info>Panty and Stocking with Garterbelt</info>
		<info>Schoolyard Heroes</info>
		<info>Violence Is All The Rage</info>
	</skit>
	<skit>
		<info>SSGWNBTD</info>
		<info>Gurren Lagann</info>
		<info>Anchorman: The Legend of Ron Burgundy</info>
		<info>Audio</info>
	</skit>
	<skit>
		<info>Zarxrax</info>
		<info>Azumanga Daioh</info>
		<info>Ol' Dirty Bastard</info>
		<info>Goin' Down</info>
	</skit>
	<skit>
		<info>Zarxrax</info>
		<info>Berserk</info>
		<info>Airplane!</info>
		<info>Sound clip</info>
	</skit>
	<skit>
		<info>Zarxrax</info>
		<info>Nichijou</info>
		<info>Filligar</info>
		<info>Sunflower Kid</info>
	</skit>
	<skit>
		<info>Zarxrax</info>
		<info>Panty and Stocking</info>
		<info>Beyonce</info>
		<info>Halo</info>
	</skit>
	<skit>
		<info>Zarxrax</info>
		<info>Puni Puni Poemi</info>
		<info>Third Impact</info>
		<info>Squid Girl</info>
	</skit>
	<skit>
		<info>Zarxrax</info>
		<info>Redline</info>
		<info>Lyude</info>
		<info>F-Zero X Big Blue remix</info>
	</skit>
	<skit>
		<info>Zarxrax</info>
		<info>Gurren Lagann Movie 2</info>
		<info>Futurama</info>
		<info>sound clip</info>
	</skit>
	<skit>
		<info>Zarxrax</info>
		<info>Evangelion 2.22</info>
		<info>Plastiscines</info>
		<info>Bitch</info>
	</skit>
	<skit>
		<info>Zarxrax</info>
		<info>Nichijou</info>
		<info>System of a Down</info>
		<info>Deer Dance</info>
	</skit>
	<skit>
		<info>Zarxrax</info>
		<info>AMV Hell 3</info>
		<info>f(x)</info>
		<info>Electric Shock</info>
	</skit>
	<skit>
		<info>Zarxrax</info>
		<info>AMV Hell 3</info>
		<info>Psy</info>
		<info>Gangnam Style</info>
	</skit>
	<skit>
		<info>Zarxrax</info>
		<info>Puni Puni Poemi</info>
		<info>Kyary Pamyu Pamyu</info>
		<info>PONPONPON</info>
	</skit>
	<skit>
		<info>Zarxrax</info>
		<info>Redline</info>
		<info>KISS</info>
		<info>Lick It Up</info>
	</skit>
	<skit>
		<info>Zarxrax</info>
		<info>Gurren Lagann Movie 2</info>
		<info>Mega Man</info>
		<info>Drill Man Jazz remix </info>
	</skit>
</skits>